pywowgen/__init__.py
pywowgen/cli.py
pywowgen/helpers.py
pywowgen/remotes.py
pywowgen/waapi.py
pywowgen/wagenerators.py
pywowgen/wamap.py
pywowgen/waresources.py
pywowgen/waworld.py
pywowgen-0.0.27.dist-info/LICENSE
pywowgen-0.0.27.dist-info/METADATA
pywowgen-0.0.27.dist-info/WHEEL
pywowgen-0.0.27.dist-info/entry_points.txt
pywowgen-0.0.27.dist-info/top_level.txt
pywowgen-0.0.27.dist-info/RECORD
