Metadata-Version: 2.1
Name: pywowgen
Version: 0.0.27
Summary: Generate and configure Workadventure worlds, maps and resources
Home-page: https://git.cccwi.de/2dwt/wowgen
Author: tigabeatz
Author-email: tigabeatz@cccwi.de
Classifier: Programming Language :: Python :: 3
Classifier: License :: OSI Approved :: MIT License
Classifier: Operating System :: OS Independent
Classifier: Development Status :: 3 - Alpha
Requires-Python: >=3.6
License-File: LICENSE
Requires-Dist: Pillow
Requires-Dist: requests
Requires-Dist: flask
Requires-Dist: GitPython
